exonamd/__init__.py
exonamd/__version__.py
exonamd/catalog.py
exonamd/core.py
exonamd/data/__init__.py
exonamd/data/custom_db_20241012.csv
exonamd/data/custom_db_20241017.csv
exonamd/data/custom_db_20241017e.csv
exonamd/data/custom_db_20241227.csv
exonamd/data/custom_db_20241227_plus_famous.csv
exonamd/data/custom_db_20250122_plus_famous.csv
exonamd/data/custom_db_20250122_plus_famous_942ecc.csv
exonamd/data/custom_db_20250122_plus_famous_942ecc_f.csv
exonamd/data/custom_db_20250811.csv
exonamd/data/custom_db_20250811_fakes.csv
exonamd/data/custom_db_20250811_interp.csv
exonamd/data/custom_db_20250811_interp_plus_fakes.csv
exonamd/data/custom_db_20250811_interp_plus_lambda.csv
exonamd/data/custom_db_20250813_plus_famous_fakes.csv
exonamd/data/custom_db_20250814.csv
exonamd/data/custom_db_20250814_interp.csv
exonamd/data/df_exo_famous.csv
exonamd/data/exo.csv
exonamd/data/exo_custom_db_20241017e.csv
exonamd/data/exo_interp.csv
exonamd/data/exo_interp_custom_db_20241017e.csv
exonamd/data/exo_namd.csv
exonamd/data/exo_namd_custom_db_20241017e.csv
exonamd/data/exonamd_database_readme.txt
exonamd/data/k462lambda.csv
exonamd/exonamd.py
exonamd/interp.py
exonamd/log.py
exonamd/plot.py
exonamd/run.py
exonamd/solve.py
exonamd/utils.py
exonamd-0.3.1.dist-info/LICENSE
exonamd-0.3.1.dist-info/METADATA
exonamd-0.3.1.dist-info/WHEEL
exonamd-0.3.1.dist-info/entry_points.txt
exonamd-0.3.1.dist-info/RECORD
