Metadata-Version: 2.3
Name: exonamd
Version: 0.3.1
Summary: ExoNAMD is a Python codebase to compute the Normalized Angular Momentum Deficit of planetary systems.
License: BSD-3-Clause
Keywords: exoplanets,planetary systems,multiplanetary systems,Python,Angular Momentum Deficit,Normalized Angular Momentum Deficit,Stellar obliquity,Planet formation,Planet evolution,Planet migration
Author: Andrea Bocchieri
Author-email: andrea.bocchieri@uniroma1.it
Requires-Python: >=3.8,<4.0
Classifier: Development Status :: 5 - Production/Stable
Classifier: Environment :: Console
Classifier: Intended Audience :: Developers
Classifier: Intended Audience :: Science/Research
Classifier: License :: OSI Approved :: BSD License
Classifier: Operating System :: OS Independent
Classifier: Programming Language :: Python :: 3
Classifier: Programming Language :: Python :: 3.8
Classifier: Programming Language :: Python :: 3.9
Classifier: Programming Language :: Python :: 3.10
Classifier: Programming Language :: Python :: 3.11
Classifier: Programming Language :: Python :: 3.12
Classifier: Programming Language :: Python :: 3.13
Classifier: Topic :: Scientific/Engineering
Classifier: Topic :: Software Development :: Libraries
Requires-Dist: astroquery
Requires-Dist: loguru
Requires-Dist: matplotlib
Requires-Dist: numpy
Requires-Dist: pandas
Requires-Dist: requests
Requires-Dist: scipy
Requires-Dist: siphash24
Requires-Dist: spright
Requires-Dist: swifter
Project-URL: Bug Tracker, https://github.com/abocchieri/ExoNAMD/issues
Project-URL: Homepage, https://github.com/abocchieri/ExoNAMD
Project-URL: Repository, https://github.com/abocchieri/ExoNAMD.git
